examples/__init__.py
examples/advanced.py
examples/simple.py
xrpl_websocket/__about__.py
xrpl_websocket/__init__.py
xrpl_websocket/client.py
xrpl_websocket/exceptions.py
xrpl_websocket-0.1.0rc2.dist-info/LICENSE
xrpl_websocket-0.1.0rc2.dist-info/METADATA
xrpl_websocket-0.1.0rc2.dist-info/WHEEL
xrpl_websocket-0.1.0rc2.dist-info/top_level.txt
xrpl_websocket-0.1.0rc2.dist-info/zip-safe
xrpl_websocket-0.1.0rc2.dist-info/RECORD
