Metadata-Version: 2.1
Name: xrpl-websocket
Version: 0.1.0rc2
Summary: XRL Websocket Client
Home-page: https://github.com/N3TC4T/python-xrpl-websocket
Author: N3TC4T
Author-email: netcat.av@gmail.com
License: Apache2
Keywords: xrp,ledger,ripple,websocket
Platform: UNKNOWN
Classifier: Development Status :: 4 - Beta
Classifier: License :: OSI Approved :: Apache Software License
Classifier: Programming Language :: Python
Classifier: Programming Language :: Python :: 2
Classifier: Programming Language :: Python :: 2.6
Classifier: Programming Language :: Python :: 2.7
Classifier: Programming Language :: Python :: 3
Classifier: Programming Language :: Python :: 3.4
Classifier: Programming Language :: Python :: 3.5
Classifier: Programming Language :: Python :: 3.6
Classifier: Programming Language :: Python :: 3.7
Classifier: Operating System :: MacOS :: MacOS X
Classifier: Operating System :: POSIX
Classifier: Operating System :: Microsoft :: Windows
Classifier: Topic :: Internet
Classifier: Topic :: Software Development :: Libraries :: Python Modules
Classifier: Intended Audience :: Developers
Requires-Python: >=2.6, !=3.0.*, !=3.1.*, !=3.2.*, !=3.3.*
Requires-Dist: websocket-client (==0.56.0)
Requires-Dist: wsaccel
